Metadata-Version: 2.4
Name: remgpt
Version: 0.2.0
Summary: A Python library for RemGPT
Author-email: Siddharth Ambegaonkar <sid.ambegaonkar@gmail.com>
License: MIT
Project-URL: Homepage, https://github.com/yourusername/remgpt
Project-URL: Repository, https://github.com/yourusername/remgpt
Classifier: Development Status :: 3 - Alpha
Classifier: Intended Audience :: Developers
Classifier: License :: OSI Approved :: MIT License
Classifier: Operating System :: OS Independent
Classifier: Programming Language :: Python :: 3
Classifier: Programming Language :: Python :: 3.8
Classifier: Programming Language :: Python :: 3.9
Classifier: Programming Language :: Python :: 3.10
Classifier: Programming Language :: Python :: 3.11
Requires-Python: >=3.8
License-File: LICENSE
Requires-Dist: pydantic>=2.0.0
Requires-Dist: tiktoken>=0.4.0
Requires-Dist: fastapi>=0.104.0
Requires-Dist: uvicorn[standard]>=0.24.0
Dynamic: license-file
